{
  "updated_at": "2026-07-24T06:10:39.078361+00:00",
  "stocks": {
    "000660": {
      "name": "SK하이닉스",
      "price": 1760000,
      "change": -159000,
      "change_rate": -8.29
    },
    "003230": {
      "name": "삼양식품",
      "price": 1147000,
      "change": 20000,
      "change_rate": 1.77
    },
    "010120": {
      "name": "LS ELECTRIC",
      "price": 201500,
      "change": -22000,
      "change_rate": -9.84
    },
    "071050": {
      "name": "한국금융지주",
      "price": 211500,
      "change": -10000,
      "change_rate": -4.51
    },
    "316140": {
      "name": "우리금융지주",
      "price": 30650,
      "change": -250,
      "change_rate": -0.81
    },
    "005930": {
      "name": "삼성전자",
      "price": 249500,
      "change": -20500,
      "change_rate": -7.59
    },
    "360750": {
      "name": "TIGER 미국S&P500",
      "price": 26940,
      "change": -340,
      "change_rate": -1.25
    },
    "418660": {
      "name": "TIGER 미국나스닥100레버리지",
      "price": 41865,
      "change": -1870,
      "change_rate": -4.28
    },
    "133690": {
      "name": "TIGER 미국나스닥100",
      "price": 184140,
      "change": -3905,
      "change_rate": -2.08
    },
    "003490": {
      "name": "대한항공",
      "price": 25550,
      "change": -200,
      "change_rate": -0.78
    },
    "016360": {
      "name": "삼성증권",
      "price": 99800,
      "change": -5100,
      "change_rate": -4.86
    },
    "GOOGL": {
      "price": 317.69,
      "change": -13.06,
      "change_rate": -3.95,
      "currency": "USD"
    },
    "UBER": {
      "price": 68.91,
      "change": -1.77,
      "change_rate": -2.5,
      "currency": "USD"
    },
    "MSFT": {
      "price": 381.58,
      "change": -6.72,
      "change_rate": -1.73,
      "currency": "USD"
    },
    "BRK.B": {
      "price": 490.85,
      "change": 1.95,
      "change_rate": 0.4,
      "currency": "USD"
    },
    "XOM": {
      "price": 156.89,
      "change": 1.72,
      "change_rate": 1.11,
      "currency": "USD"
    },
    "DRAM": {
      "price": 58.3,
      "change": -0.77,
      "change_rate": -1.31,
      "currency": "USD"
    }
  },
  "indices": {
    "KOSPI": {
      "price": 6684.38,
      "change": -412.51,
      "change_rate": -5.81
    },
    "KOSDAQ": {
      "price": 748.1,
      "change": -42.18,
      "change_rate": -5.34
    },
    "SPX": {
      "price": 7408.3,
      "change": -90.66,
      "change_rate": -1.21
    },
    "NASDAQ": {
      "price": 25137.69,
      "change": -553.21,
      "change_rate": -2.15
    },
    "DJI": {
      "price": 51711.65,
      "change": -506.93,
      "change_rate": -0.97
    }
  }
}